[
  {
    "uri": "en/12/744649",
    "id": "744649",
    "lang": "en",
    "classNumber": "12",
    "term": "Linear motors for land vehicles",
    "harm": {
      "id": "0014500",
      "title": "744649 - Linear motors for land vehicles",
      "conceptLink": "/ec2/concept/5964736"
    }
  },
  {
    "uri": "en/12/193202",
    "id": "193202",
    "lang": "en",
    "classNumber": "12",
    "term": "Linings (Brake -) for vehicles",
    "harm": {
      "id": "0025293",
      "title": "193202 - Linings (Brake -) for vehicles",
      "conceptLink": "/ec2/concept/5974612"
    }
  },
  {
    "uri": "en/12/193201",
    "id": "193201",
    "lang": "en",
    "classNumber": "12",
    "term": "Linings for brakes of vehicles",
    "harm": {
      "id": "0025293",
      "title": "193201 - Linings for brakes of vehicles",
      "conceptLink": "/ec2/concept/5974612"
    }
  },
  {
    "uri": "en/12/744662",
    "id": "744662",
    "lang": "en",
    "classNumber": "12",
    "term": "Linings for vehicles",
    "harm": {
      "id": "0026002",
      "title": "744662 - Linings for vehicles",
      "conceptLink": "/ec2/concept/5975267"
    }
  },
  {
    "uri": "en/12/744673",
    "id": "744673",
    "lang": "en",
    "classNumber": "12",
    "term": "Link chains for driving purposes [for land vehicles]",
    "harm": {
      "id": "0020329",
      "title": "744673 - Link chains for driving purposes [for land vehicles]",
      "conceptLink": "/ec2/concept/5970060"
    }
  },
  {
    "uri": "en/12/744686",
    "id": "744686",
    "lang": "en",
    "classNumber": "12",
    "term": "Livestock trailers",
    "harm": {
      "id": "0008643",
      "title": "744686 - Livestock trailers",
      "conceptLink": "/ec2/concept/5959356"
    }
  },
  {
    "uri": "en/12/744700",
    "id": "744700",
    "lang": "en",
    "classNumber": "12",
    "term": "Load bearing sections for chassis frames of vehicles",
    "harm": {
      "id": "0014501",
      "title": "744700 - Load bearing sections for chassis frames of vehicles",
      "conceptLink": "/ec2/concept/5964737"
    }
  },
  {
    "uri": "en/12/744712",
    "id": "744712",
    "lang": "en",
    "classNumber": "12",
    "term": "Load carrying [lifting] attachments for motor vehicles",
    "harm": {
      "id": "0031794",
      "title": "744712 - Load carrying [lifting] attachments for motor vehicles",
      "conceptLink": "/ec2/concept/5980554"
    }
  },
  {
    "uri": "en/12/411017",
    "id": "411017",
    "lang": "en",
    "classNumber": "12",
    "term": "Load carrying trailers",
    "harm": {
      "id": "0057532",
      "title": "411017 - Load carrying trailers",
      "conceptLink": "/ec2/concept/5999037"
    }
  },
  {
    "uri": "en/12/744725",
    "id": "744725",
    "lang": "en",
    "classNumber": "12",
    "term": "Load carrying vehicles",
    "harm": {
      "id": "0006116",
      "title": "744725 - Load carrying vehicles",
      "conceptLink": "/ec2/concept/5957058"
    }
  },
  {
    "uri": "en/12/744737",
    "id": "744737",
    "lang": "en",
    "classNumber": "12",
    "term": "Loader swivel axle bogies for vehicles",
    "harm": {
      "id": "0035006",
      "title": "744737 - Loader swivel axle bogies for vehicles",
      "conceptLink": "/ec2/concept/5983483"
    }
  },
  {
    "uri": "en/12/744749",
    "id": "744749",
    "lang": "en",
    "classNumber": "12",
    "term": "Loader swivel axles for vehicles",
    "harm": {
      "id": "0011899",
      "title": "744749 - Loader swivel axles for vehicles",
      "conceptLink": "/ec2/concept/5962350"
    }
  },
  {
    "uri": "en/12/744761",
    "id": "744761",
    "lang": "en",
    "classNumber": "12",
    "term": "Loaders [fork-lift trucks]",
    "harm": {
      "id": "0035007",
      "title": "744761 - Loaders [fork-lift trucks]",
      "conceptLink": "/ec2/concept/5983484"
    }
  },
  {
    "uri": "en/12/190071",
    "id": "190071",
    "lang": "en",
    "classNumber": "12",
    "term": "Locomotives",
    "harm": {
      "id": "0004908",
      "title": "190071 - Locomotives",
      "conceptLink": "/ec2/concept/5955953"
    }
  },
  {
    "uri": "en/12/744777",
    "id": "744777",
    "lang": "en",
    "classNumber": "12",
    "term": "Locomotives for transporting freight",
    "harm": {
      "id": "0011900",
      "title": "744777 - Locomotives for transporting freight",
      "conceptLink": "/ec2/concept/5962351"
    }
  },
  {
    "uri": "en/12/189883",
    "id": "189883",
    "lang": "en",
    "classNumber": "12",
    "term": "Loose seat covers [shaped] for vehicle seats",
    "harm": {
      "id": "0046874",
      "title": "189883 - Loose seat covers [shaped] for vehicle seats",
      "conceptLink": "/ec2/concept/5994266"
    }
  },
  {
    "uri": "en/12/184228",
    "id": "184228",
    "lang": "en",
    "classNumber": "12",
    "term": "Lorries",
    "harm": {
      "id": "0046325",
      "title": "184228 - Lorries",
      "conceptLink": "/ec2/concept/5993784"
    }
  },
  {
    "uri": "en/12/337905",
    "id": "337905",
    "lang": "en",
    "classNumber": "12",
    "term": "Lorries for mines",
    "harm": {
      "id": "0039609",
      "title": "337905 - Lorries for mines",
      "conceptLink": "/ec2/concept/5987669"
    }
  },
  {
    "uri": "en/12/411974",
    "id": "411974",
    "lang": "en",
    "classNumber": "12",
    "term": "Lug nuts for vehicle wheels",
    "harm": {
      "id": "0001701",
      "title": "411974 - Lug nuts for vehicle wheels",
      "conceptLink": "/ec2/concept/5953015"
    }
  },
  {
    "uri": "en/12/744789",
    "id": "744789",
    "lang": "en",
    "classNumber": "12",
    "term": "Luggage carriers for attachment to vehicles",
    "harm": {
      "id": "0011901",
      "title": "744789 - Luggage carriers for attachment to vehicles",
      "conceptLink": "/ec2/concept/5962352"
    }
  },
  {
    "uri": "en/12/12917783",
    "id": "12917783",
    "lang": "en",
    "classNumber": "12",
    "term": "Luggage carriers for automobiles",
    "harm": {
      "id": "0012271",
      "title": "12917783 - Luggage carriers for automobiles",
      "conceptLink": "/ec2/concept/5962692"
    }
  },
  {
    "uri": "en/12/497145",
    "id": "497145",
    "lang": "en",
    "classNumber": "12",
    "term": "Luggage carriers for bicycles",
    "harm": {
      "id": "0017659",
      "title": "497145 - Luggage carriers for bicycles",
      "conceptLink": "/ec2/concept/5967618"
    }
  },
  {
    "uri": "en/12/497146",
    "id": "497146",
    "lang": "en",
    "classNumber": "12",
    "term": "Luggage carriers for cycles",
    "harm": {
      "id": "0017659",
      "title": "497146 - Luggage carriers for cycles",
      "conceptLink": "/ec2/concept/5967618"
    }
  },
  {
    "uri": "en/12/120894979",
    "id": "120894979",
    "lang": "en",
    "classNumber": "12",
    "term": "Luggage carriers for motorcycles",
    "harm": {
      "id": "0066337",
      "title": "120894979 - Luggage carriers for motorcycles",
      "conceptLink": "/ec2/concept/6002540"
    }
  },
  {
    "uri": "en/12/184573",
    "id": "184573",
    "lang": "en",
    "classNumber": "12",
    "term": "Luggage carriers for vehicles",
    "harm": {
      "id": "0057889",
      "title": "184573 - Luggage carriers for vehicles",
      "conceptLink": "/ec2/concept/5999393"
    }
  },
  {
    "uri": "en/12/189326",
    "id": "189326",
    "lang": "en",
    "classNumber": "12",
    "term": "Luggage nets for vehicles",
    "harm": {
      "id": "0047062",
      "title": "189326 - Luggage nets for vehicles",
      "conceptLink": "/ec2/concept/5994439"
    }
  },
  {
    "uri": "en/12/337920",
    "id": "337920",
    "lang": "en",
    "classNumber": "12",
    "term": "Luggage racks fitted to the bonnet",
    "harm": {
      "id": "0022420",
      "title": "337920 - Luggage racks fitted to the bonnet",
      "conceptLink": "/ec2/concept/5971976"
    }
  },
  {
    "uri": "en/12/120895106",
    "id": "120895106",
    "lang": "en",
    "classNumber": "12",
    "term": "Luggage racks for attachment to vehicle boots",
    "harm": {
      "id": "0066329",
      "title": "120895106 - Luggage racks for attachment to vehicle boots",
      "conceptLink": "/ec2/concept/6002532"
    }
  },
  {
    "uri": "en/12/120895101",
    "id": "120895101",
    "lang": "en",
    "classNumber": "12",
    "term": "Luggage racks for attachment to vehicle hoods",
    "harm": {
      "id": "0066330",
      "title": "120895101 - Luggage racks for attachment to vehicle hoods",
      "conceptLink": "/ec2/concept/6002533"
    }
  },
  {
    "uri": "en/12/137703891",
    "id": "137703891",
    "lang": "en",
    "classNumber": "12",
    "term": "Luggage racks for bicycles",
    "harm": {
      "id": "0017659",
      "title": "137703891 - Luggage racks for bicycles",
      "conceptLink": "/ec2/concept/5967618"
    }
  },
  {
    "uri": "en/12/124044227",
    "id": "124044227",
    "lang": "en",
    "classNumber": "12",
    "term": "Luggage racks for cycles",
    "harm": {
      "id": "0017659",
      "title": "124044227 - Luggage racks for cycles",
      "conceptLink": "/ec2/concept/5967618"
    }
  },
  {
    "uri": "en/12/337932",
    "id": "337932",
    "lang": "en",
    "classNumber": "12",
    "term": "Luggage racks for motor cars",
    "harm": {
      "id": "0012271",
      "title": "337932 - Luggage racks for motor cars",
      "conceptLink": "/ec2/concept/5962692"
    }
  },
  {
    "uri": "en/12/32281442",
    "id": "32281442",
    "lang": "en",
    "classNumber": "12",
    "term": "Luggage racks for motorcycles",
    "harm": {
      "id": "0066337",
      "title": "32281442 - Luggage racks for motorcycles",
      "conceptLink": "/ec2/concept/6002540"
    }
  },
  {
    "uri": "en/12/184575",
    "id": "184575",
    "lang": "en",
    "classNumber": "12",
    "term": "Luggage racks for vehicles",
    "harm": {
      "id": "0057889",
      "title": "184575 - Luggage racks for vehicles",
      "conceptLink": "/ec2/concept/5999393"
    }
  },
  {
    "uri": "en/12/186132",
    "id": "186132",
    "lang": "en",
    "classNumber": "12",
    "term": "Luggage trucks",
    "harm": {
      "id": "0005609",
      "title": "186132 - Luggage trucks",
      "conceptLink": "/ec2/concept/5956598"
    }
  },
  {
    "uri": "en/12/744803",
    "id": "744803",
    "lang": "en",
    "classNumber": "12",
    "term": "Mail trolleys",
    "harm": {
      "id": "0040805",
      "title": "744803 - Mail trolleys",
      "conceptLink": "/ec2/concept/5988767"
    }
  },
  {
    "uri": "en/12/337173",
    "id": "337173",
    "lang": "en",
    "classNumber": "12",
    "term": "Main brake cylinders",
    "harm": {
      "id": "0029614",
      "title": "337173 - Main brake cylinders",
      "conceptLink": "/ec2/concept/5978573"
    }
  },
  {
    "uri": "en/12/411994",
    "id": "411994",
    "lang": "en",
    "classNumber": "12",
    "term": "Manual wheelchairs",
    "harm": {
      "id": "0029228",
      "title": "411994 - Manual wheelchairs",
      "conceptLink": "/ec2/concept/5978224"
    }
  },
  {
    "uri": "en/12/411995",
    "id": "411995",
    "lang": "en",
    "classNumber": "12",
    "term": "Manually operated wheelchairs",
    "harm": {
      "id": "0029228",
      "title": "411995 - Manually operated wheelchairs",
      "conceptLink": "/ec2/concept/5978224"
    }
  },
  {
    "uri": "en/12/184093",
    "id": "184093",
    "lang": "en",
    "classNumber": "12",
    "term": "Marine craft",
    "harm": {
      "id": "0000893",
      "title": "184093 - Marine craft",
      "conceptLink": "/ec2/concept/5952292"
    }
  },
  {
    "uri": "en/12/744815",
    "id": "744815",
    "lang": "en",
    "classNumber": "12",
    "term": "Marine masts",
    "harm": {
      "id": "0000327",
      "title": "744815 - Marine masts",
      "conceptLink": "/ec2/concept/5951784"
    }
  },
  {
    "uri": "en/12/744828",
    "id": "744828",
    "lang": "en",
    "classNumber": "12",
    "term": "Marine porthole frames",
    "harm": {
      "id": "0044825",
      "title": "744828 - Marine porthole frames",
      "conceptLink": "/ec2/concept/5992438"
    }
  },
  {
    "uri": "en/12/744841",
    "id": "744841",
    "lang": "en",
    "classNumber": "12",
    "term": "Marine porthole window closures",
    "harm": {
      "id": "0022930",
      "title": "744841 - Marine porthole window closures",
      "conceptLink": "/ec2/concept/5972441"
    }
  },
  {
    "uri": "en/12/185352",
    "id": "185352",
    "lang": "en",
    "classNumber": "12",
    "term": "Marine propellers",
    "harm": {
      "id": "0072693",
      "title": "185352 - Marine propellers",
      "conceptLink": "/ec2/concept/6008870"
    }
  },
  {
    "uri": "en/12/190620",
    "id": "190620",
    "lang": "en",
    "classNumber": "12",
    "term": "Marine vehicles",
    "harm": {
      "id": "0024847",
      "title": "190620 - Marine vehicles",
      "conceptLink": "/ec2/concept/5974211"
    }
  },
  {
    "uri": "en/12/493728",
    "id": "493728",
    "lang": "en",
    "classNumber": "12",
    "term": "Masts for boats",
    "harm": {
      "id": "0025972",
      "title": "493728 - Masts for boats",
      "conceptLink": "/ec2/concept/5975237"
    }
  },
  {
    "uri": "en/12/744853",
    "id": "744853",
    "lang": "en",
    "classNumber": "12",
    "term": "Mechanical gearings for land vehicles",
    "harm": {
      "id": "0005527",
      "title": "744853 - Mechanical gearings for land vehicles",
      "conceptLink": "/ec2/concept/5956522"
    }
  },
  {
    "uri": "en/12/744865",
    "id": "744865",
    "lang": "en",
    "classNumber": "12",
    "term": "Mechanical handling trucks",
    "harm": {
      "id": "0028569",
      "title": "744865 - Mechanical handling trucks",
      "conceptLink": "/ec2/concept/5977613"
    }
  },
  {
    "uri": "en/12/744878",
    "id": "744878",
    "lang": "en",
    "classNumber": "12",
    "term": "Mechanical power transmitting mechanisms for land vehicles",
    "harm": {
      "id": "0005526",
      "title": "744878 - Mechanical power transmitting mechanisms for land vehicles",
      "conceptLink": "/ec2/concept/5956521"
    }
  },
  {
    "uri": "en/12/190336",
    "id": "190336",
    "lang": "en",
    "classNumber": "12",
    "term": "Mechanical transmissions for land vehicles",
    "harm": {
      "id": "0005527",
      "title": "190336 - Mechanical transmissions for land vehicles",
      "conceptLink": "/ec2/concept/5956522"
    }
  },
  {
    "uri": "en/12/412021",
    "id": "412021",
    "lang": "en",
    "classNumber": "12",
    "term": "Mechanics' creepers",
    "harm": {
      "id": "0036390",
      "title": "412021 - Mechanics' creepers",
      "conceptLink": "/ec2/concept/5984739"
    }
  },
  {
    "uri": "en/12/744890",
    "id": "744890",
    "lang": "en",
    "classNumber": "12",
    "term": "Metal bells for bicycles",
    "harm": {
      "id": "0040131",
      "title": "744890 - Metal bells for bicycles",
      "conceptLink": "/ec2/concept/5988151"
    }
  },
  {
    "uri": "en/12/137927135",
    "id": "137927135",
    "lang": "en",
    "classNumber": "12",
    "term": "Metal laminated leaf springs for vehicle suspensions",
    "harm": {
      "id": "0071708",
      "title": "137927135 - Metal laminated leaf springs for vehicle suspensions",
      "conceptLink": "/ec2/concept/6007896"
    }
  },
  {
    "uri": "en/12/744903",
    "id": "744903",
    "lang": "en",
    "classNumber": "12",
    "term": "Metal masts for watercraft",
    "harm": {
      "id": "0022931",
      "title": "744903 - Metal masts for watercraft",
      "conceptLink": "/ec2/concept/5972442"
    }
  },
  {
    "uri": "en/12/744915",
    "id": "744915",
    "lang": "en",
    "classNumber": "12",
    "term": "Metal poles being masts for watercraft",
    "harm": {
      "id": "0011262",
      "title": "744915 - Metal poles being masts for watercraft",
      "conceptLink": "/ec2/concept/5961766"
    }
  },
  {
    "uri": "en/12/744928",
    "id": "744928",
    "lang": "en",
    "classNumber": "12",
    "term": "Metal studs for vehicle tyres",
    "harm": {
      "id": "0045856",
      "title": "744928 - Metal studs for vehicle tyres",
      "conceptLink": "/ec2/concept/5993386"
    }
  },
  {
    "uri": "en/12/744940",
    "id": "744940",
    "lang": "en",
    "classNumber": "12",
    "term": "Military aircraft",
    "harm": {
      "id": "0045857",
      "title": "744940 - Military aircraft",
      "conceptLink": "/ec2/concept/5993387"
    }
  },
  {
    "uri": "en/12/137728804",
    "id": "137728804",
    "lang": "en",
    "classNumber": "12",
    "term": "Military drones",
    "harm": {
      "id": "0069918",
      "title": "137728804 - Military drones",
      "conceptLink": "/ec2/concept/6006121"
    }
  },
  {
    "uri": "en/12/190504",
    "id": "190504",
    "lang": "en",
    "classNumber": "12",
    "term": "Military vehicles for transport",
    "harm": {
      "id": "0006182",
      "title": "190504 - Military vehicles for transport",
      "conceptLink": "/ec2/concept/5957117"
    }
  },
  {
    "uri": "en/12/337946",
    "id": "337946",
    "lang": "en",
    "classNumber": "12",
    "term": "Mine-car pullers",
    "harm": {
      "id": "0023884",
      "title": "337946 - Mine-car pullers",
      "conceptLink": "/ec2/concept/5973315"
    }
  },
  {
    "uri": "en/12/337960",
    "id": "337960",
    "lang": "en",
    "classNumber": "12",
    "term": "Mine-car pushers",
    "harm": {
      "id": "0023885",
      "title": "337960 - Mine-car pushers",
      "conceptLink": "/ec2/concept/5973316"
    }
  },
  {
    "uri": "en/12/185585",
    "id": "185585",
    "lang": "en",
    "classNumber": "12",
    "term": "Mine cart wheels",
    "harm": {
      "id": "0058601",
      "title": "185585 - Mine cart wheels",
      "conceptLink": "/ec2/concept/6000094"
    }
  },
  {
    "uri": "en/12/744953",
    "id": "744953",
    "lang": "en",
    "classNumber": "12",
    "term": "Minesweepers [ships]",
    "harm": {
      "id": "0017056",
      "title": "744953 - Minesweepers [ships]",
      "conceptLink": "/ec2/concept/5967074"
    }
  },
  {
    "uri": "en/12/412034",
    "id": "412034",
    "lang": "en",
    "classNumber": "12",
    "term": "Mini-bikes",
    "harm": {
      "id": "0024848",
      "title": "412034 - Mini-bikes",
      "conceptLink": "/ec2/concept/5974212"
    }
  },
  {
    "uri": "en/12/412059",
    "id": "412059",
    "lang": "en",
    "classNumber": "12",
    "term": "Minibuses",
    "harm": {
      "id": "0026256",
      "title": "412059 - Minibuses",
      "conceptLink": "/ec2/concept/5975497"
    }
  },
  {
    "uri": "en/12/412058",
    "id": "412058",
    "lang": "en",
    "classNumber": "12",
    "term": "Minivans",
    "harm": {
      "id": "0026256",
      "title": "412058 - Minivans",
      "conceptLink": "/ec2/concept/5975497"
    }
  },
  {
    "uri": "en/12/412090",
    "id": "412090",
    "lang": "en",
    "classNumber": "12",
    "term": "Mirrors for vehicles",
    "harm": {
      "id": "0042117",
      "title": "412090 - Mirrors for vehicles",
      "conceptLink": "/ec2/concept/5989965"
    }
  },
  {
    "uri": "en/12/191777",
    "id": "191777",
    "lang": "en",
    "classNumber": "12",
    "term": "Mirrors (Rearview -)",
    "harm": {
      "id": "0011994",
      "title": "191777 - Mirrors (Rearview -)",
      "conceptLink": "/ec2/concept/5962440"
    }
  },
  {
    "uri": "en/12/412117",
    "id": "412117",
    "lang": "en",
    "classNumber": "12",
    "term": "Mirrors [rearview] for vehicles",
    "harm": {
      "id": "0042117",
      "title": "412117 - Mirrors [rearview] for vehicles",
      "conceptLink": "/ec2/concept/5989965"
    }
  },
  {
    "uri": "en/12/744966",
    "id": "744966",
    "lang": "en",
    "classNumber": "12",
    "term": "Mobile fork lifts",
    "harm": {
      "id": "0015810",
      "title": "744966 - Mobile fork lifts",
      "conceptLink": "/ec2/concept/5965938"
    }
  },
  {
    "uri": "en/12/186344",
    "id": "186344",
    "lang": "en",
    "classNumber": "12",
    "term": "Mobile homes [caravans]",
    "harm": {
      "id": "0046320",
      "title": "186344 - Mobile homes [caravans]",
      "conceptLink": "/ec2/concept/5993780"
    }
  },
  {
    "uri": "en/12/412145",
    "id": "412145",
    "lang": "en",
    "classNumber": "12",
    "term": "Mobile railcar movers",
    "harm": {
      "id": "0003171",
      "title": "412145 - Mobile railcar movers",
      "conceptLink": "/ec2/concept/5954353"
    }
  },
  {
    "uri": "en/12/120918974",
    "id": "120918974",
    "lang": "en",
    "classNumber": "12",
    "term": "Mobility conveyances",
    "harm": {
      "id": "0047806",
      "title": "120918974 - Mobility conveyances",
      "conceptLink": "/ec2/concept/5995081"
    }
  },
  {
    "uri": "en/12/7294057",
    "id": "7294057",
    "lang": "en",
    "classNumber": "12",
    "term": "Mobility scooters",
    "harm": {
      "id": "0069925",
      "title": "7294057 - Mobility scooters",
      "conceptLink": "/ec2/concept/6006128"
    }
  },
  {
    "uri": "en/12/412160",
    "id": "412160",
    "lang": "en",
    "classNumber": "12",
    "term": "Mobility vehicles",
    "harm": {
      "id": "0037841",
      "title": "412160 - Mobility vehicles",
      "conceptLink": "/ec2/concept/5986052"
    }
  },
  {
    "uri": "en/12/412178",
    "id": "412178",
    "lang": "en",
    "classNumber": "12",
    "term": "Modular chassis systems for vehicles",
    "harm": {
      "id": "0008916",
      "title": "412178 - Modular chassis systems for vehicles",
      "conceptLink": "/ec2/concept/5959612"
    }
  },
  {
    "uri": "en/12/744991",
    "id": "744991",
    "lang": "en",
    "classNumber": "12",
    "term": "Monocoque structures for vehicles",
    "harm": {
      "id": "0021697",
      "title": "744991 - Monocoque structures for vehicles",
      "conceptLink": "/ec2/concept/5971308"
    }
  },
  {
    "uri": "en/12/744979",
    "id": "744979",
    "lang": "en",
    "classNumber": "12",
    "term": "Monocoque structures for aircraft",
    "harm": {
      "id": "0009982",
      "title": "744979 - Monocoque structures for aircraft",
      "conceptLink": "/ec2/concept/5960594"
    }
  },
  {
    "uri": "en/12/745003",
    "id": "745003",
    "lang": "en",
    "classNumber": "12",
    "term": "Monorail carriages",
    "harm": {
      "id": "0004258",
      "title": "745003 - Monorail carriages",
      "conceptLink": "/ec2/concept/5955346"
    }
  },
  {
    "uri": "en/12/187943",
    "id": "187943",
    "lang": "en",
    "classNumber": "12",
    "term": "Mopeds",
    "harm": {
      "id": "0046441",
      "title": "187943 - Mopeds",
      "conceptLink": "/ec2/concept/5993892"
    }
  },
  {
    "uri": "en/12/183996",
    "id": "183996",
    "lang": "en",
    "classNumber": "12",
    "term": "Motor buses",
    "harm": {
      "id": "0059369",
      "title": "183996 - Motor buses",
      "conceptLink": "/ec2/concept/6000851"
    }
  },
  {
    "uri": "en/12/337976",
    "id": "337976",
    "lang": "en",
    "classNumber": "12",
    "term": "Motor car convertible tops",
    "harm": {
      "id": "0029615",
      "title": "337976 - Motor car convertible tops",
      "conceptLink": "/ec2/concept/5978574"
    }
  },
  {
    "uri": "en/12/189470",
    "id": "189470",
    "lang": "en",
    "classNumber": "12",
    "term": "Motor car derived vans",
    "harm": {
      "id": "0001458",
      "title": "189470 - Motor car derived vans",
      "conceptLink": "/ec2/concept/5952800"
    }
  },
  {
    "uri": "en/12/190987",
    "id": "190987",
    "lang": "en",
    "classNumber": "12",
    "term": "Motor car doors",
    "harm": {
      "id": "0029616",
      "title": "190987 - Motor car doors",
      "conceptLink": "/ec2/concept/5978575"
    }
  },
  {
    "uri": "en/12/191975",
    "id": "191975",
    "lang": "en",
    "classNumber": "12",
    "term": "Motor car seats",
    "harm": {
      "id": "0046312",
      "title": "191975 - Motor car seats",
      "conceptLink": "/ec2/concept/5993772"
    }
  },
  {
    "uri": "en/12/192610",
    "id": "192610",
    "lang": "en",
    "classNumber": "12",
    "term": "Motor car windows",
    "harm": {
      "id": "0046575",
      "title": "192610 - Motor car windows",
      "conceptLink": "/ec2/concept/5994005"
    }
  },
  {
    "uri": "en/12/194343",
    "id": "194343",
    "lang": "en",
    "classNumber": "12",
    "term": "Motor caravans",
    "harm": {
      "id": "0057067",
      "title": "194343 - Motor caravans",
      "conceptLink": "/ec2/concept/5998700"
    }
  },
  {
    "uri": "en/12/190120",
    "id": "190120",
    "lang": "en",
    "classNumber": "12",
    "term": "Motor cars",
    "harm": {
      "id": "0059411",
      "title": "190120 - Motor cars",
      "conceptLink": "/ec2/concept/6000889"
    }
  },
  {
    "uri": "en/12/338211",
    "id": "338211",
    "lang": "en",
    "classNumber": "12",
    "term": "Motor cars for racing",
    "harm": {
      "id": "0033090",
      "title": "338211 - Motor cars for racing",
      "conceptLink": "/ec2/concept/5981739"
    }
  },
  {
    "uri": "en/12/337988",
    "id": "337988",
    "lang": "en",
    "classNumber": "12",
    "term": "Motor cars for transport on land",
    "harm": {
      "id": "0012273",
      "title": "337988 - Motor cars for transport on land",
      "conceptLink": "/ec2/concept/5962694"
    }
  },
  {
    "uri": "en/12/183993",
    "id": "183993",
    "lang": "en",
    "classNumber": "12",
    "term": "Motor coaches",
    "harm": {
      "id": "0059370",
      "title": "183993 - Motor coaches",
      "conceptLink": "/ec2/concept/6000852"
    }
  },
  {
    "uri": "en/12/185706",
    "id": "185706",
    "lang": "en",
    "classNumber": "12",
    "term": "Motor cycles",
    "harm": {
      "id": "0046456",
      "title": "185706 - Motor cycles",
      "conceptLink": "/ec2/concept/5993905"
    }
  },
  {
    "uri": "en/12/190338",
    "id": "190338",
    "lang": "en",
    "classNumber": "12",
    "term": "Motor drive mechanisms for land vehicles",
    "harm": {
      "id": "0027576",
      "title": "190338 - Motor drive mechanisms for land vehicles",
      "conceptLink": "/ec2/concept/5976695"
    }
  },
  {
    "uri": "en/12/894036",
    "id": "894036",
    "lang": "en",
    "classNumber": "12",
    "term": "Motor drive units for land vehicles",
    "harm": {
      "id": "0021952",
      "title": "894036 - Motor drive units for land vehicles",
      "conceptLink": "/ec2/concept/5971547"
    }
  },
  {
    "uri": "en/12/194342",
    "id": "194342",
    "lang": "en",
    "classNumber": "12",
    "term": "Motor homes",
    "harm": {
      "id": "0057067",
      "title": "194342 - Motor homes",
      "conceptLink": "/ec2/concept/5998700"
    }
  },
  {
    "uri": "en/12/189738",
    "id": "189738",
    "lang": "en",
    "classNumber": "12",
    "term": "Motor land vehicle engines",
    "harm": {
      "id": "0058481",
      "title": "189738 - Motor land vehicle engines",
      "conceptLink": "/ec2/concept/5999980"
    }
  },
  {
    "uri": "en/12/189732",
    "id": "189732",
    "lang": "en",
    "classNumber": "12",
    "term": "Motor land vehicles",
    "harm": {
      "id": "0046323",
      "title": "189732 - Motor land vehicles",
      "conceptLink": "/ec2/concept/5993782"
    }
  },
  {
    "uri": "en/12/184233",
    "id": "184233",
    "lang": "en",
    "classNumber": "12",
    "term": "Motor lorries",
    "harm": {
      "id": "0046325",
      "title": "184233 - Motor lorries",
      "conceptLink": "/ec2/concept/5993784"
    }
  },
  {
    "uri": "en/12/99000145",
    "id": "99000145",
    "lang": "en",
    "classNumber": "12",
    "term": "Motor racing cars",
    "harm": {
      "id": "0033090",
      "title": "99000145 - Motor racing cars",
      "conceptLink": "/ec2/concept/5981739"
    }
  },
  {
    "uri": "en/12/412315",
    "id": "412315",
    "lang": "en",
    "classNumber": "12",
    "term": "Motor scooters",
    "harm": {
      "id": "0035898",
      "title": "412315 - Motor scooters",
      "conceptLink": "/ec2/concept/5984287"
    }
  }
]