[
  {
    "uri": "en/41/137810982",
    "id": "137810982",
    "lang": "en",
    "classNumber": "41",
    "term": "Educational services provided by colleges",
    "harm": {
      "id": "0051011",
      "title": "137810982 - Educational services provided by colleges",
      "conceptLink": "/ec2/concept/6009997"
    }
  },
  {
    "uri": "en/41/137805193",
    "id": "137805193",
    "lang": "en",
    "classNumber": "41",
    "term": "Educational services provided by beauty schools",
    "harm": {
      "id": "0039913",
      "title": "137805193 - Educational services provided by beauty schools",
      "conceptLink": "/ec2/concept/5987953"
    }
  },
  {
    "uri": "en/41/137825444",
    "id": "137825444",
    "lang": "en",
    "classNumber": "41",
    "term": "Educational services provided by academies",
    "harm": {
      "id": "0057715",
      "title": "137825444 - Educational services provided by academies",
      "conceptLink": "/ec2/concept/5999219"
    }
  },
  {
    "uri": "en/41/120869789",
    "id": "120869789",
    "lang": "en",
    "classNumber": "41",
    "term": "Educational services provided by schools",
    "harm": {
      "id": "0046209",
      "title": "120869789 - Educational services provided by schools",
      "conceptLink": "/ec2/concept/5993698"
    }
  },
  {
    "uri": "en/41/849482",
    "id": "849482",
    "lang": "en",
    "classNumber": "41",
    "term": "Educational services relating to brewing",
    "harm": {
      "id": "0003632",
      "title": "849482 - Educational services relating to brewing",
      "conceptLink": "/ec2/concept/5954776"
    }
  },
  {
    "uri": "en/41/56251",
    "id": "56251",
    "lang": "en",
    "classNumber": "41",
    "term": "Educational services relating to sports",
    "harm": {
      "id": "0004451",
      "title": "56251 - Educational services relating to sports",
      "conceptLink": "/ec2/concept/5955524"
    }
  },
  {
    "uri": "en/41/848710",
    "id": "848710",
    "lang": "en",
    "classNumber": "41",
    "term": "Educational services relating to physical fitness",
    "harm": {
      "id": "0011404",
      "title": "848710 - Educational services relating to physical fitness",
      "conceptLink": "/ec2/concept/5961893"
    }
  },
  {
    "uri": "en/41/848366",
    "id": "848366",
    "lang": "en",
    "classNumber": "41",
    "term": "Educational services relating to cooking",
    "harm": {
      "id": "0011869",
      "title": "848366 - Educational services relating to cooking",
      "conceptLink": "/ec2/concept/5962321"
    }
  },
  {
    "uri": "en/41/849601",
    "id": "849601",
    "lang": "en",
    "classNumber": "41",
    "term": "Educational services relating to the conservation of nature",
    "harm": {
      "id": "0027514",
      "title": "849601 - Educational services relating to the conservation of nature",
      "conceptLink": "/ec2/concept/5976633"
    }
  },
  {
    "uri": "en/41/849626",
    "id": "849626",
    "lang": "en",
    "classNumber": "41",
    "term": "Educational services relating to the teaching of french",
    "harm": {
      "id": "0027515",
      "title": "849626 - Educational services relating to the teaching of french",
      "conceptLink": "/ec2/concept/5976634"
    }
  },
  {
    "uri": "en/41/849536",
    "id": "849536",
    "lang": "en",
    "classNumber": "41",
    "term": "Educational services relating to oenology",
    "harm": {
      "id": "0017205",
      "title": "849536 - Educational services relating to oenology",
      "conceptLink": "/ec2/concept/5967209"
    }
  },
  {
    "uri": "en/41/849548",
    "id": "849548",
    "lang": "en",
    "classNumber": "41",
    "term": "Educational services relating to religious development",
    "harm": {
      "id": "0017206",
      "title": "849548 - Educational services relating to religious development",
      "conceptLink": "/ec2/concept/5967210"
    }
  },
  {
    "uri": "en/41/849563",
    "id": "849563",
    "lang": "en",
    "classNumber": "41",
    "term": "Educational services relating to sales training",
    "harm": {
      "id": "0017207",
      "title": "849563 - Educational services relating to sales training",
      "conceptLink": "/ec2/concept/5967211"
    }
  },
  {
    "uri": "en/41/848397",
    "id": "848397",
    "lang": "en",
    "classNumber": "41",
    "term": "Educational services relating to data processing",
    "harm": {
      "id": "0000316",
      "title": "848397 - Educational services relating to data processing",
      "conceptLink": "/ec2/concept/5951777"
    }
  },
  {
    "uri": "en/41/849467",
    "id": "849467",
    "lang": "en",
    "classNumber": "41",
    "term": "Educational services relating to beauty therapy",
    "harm": {
      "id": "0009365",
      "title": "849467 - Educational services relating to beauty therapy",
      "conceptLink": "/ec2/concept/5960032"
    }
  },
  {
    "uri": "en/41/848539",
    "id": "848539",
    "lang": "en",
    "classNumber": "41",
    "term": "Educational services relating to management",
    "harm": {
      "id": "0010153",
      "title": "848539 - Educational services relating to management",
      "conceptLink": "/ec2/concept/5960747"
    }
  },
  {
    "uri": "en/41/849653",
    "id": "849653",
    "lang": "en",
    "classNumber": "41",
    "term": "Educational services relating to zoology",
    "harm": {
      "id": "0010150",
      "title": "849653 - Educational services relating to zoology",
      "conceptLink": "/ec2/concept/5960744"
    }
  },
  {
    "uri": "en/41/849589",
    "id": "849589",
    "lang": "en",
    "classNumber": "41",
    "term": "Educational services relating to textile manufacture",
    "harm": {
      "id": "0033283",
      "title": "849589 - Educational services relating to textile manufacture",
      "conceptLink": "/ec2/concept/5981914"
    }
  },
  {
    "uri": "en/41/137699265",
    "id": "137699265",
    "lang": "en",
    "classNumber": "41",
    "term": "Educational services relating to road safety",
    "harm": {
      "id": "0033909",
      "title": "137699265 - Educational services relating to road safety",
      "conceptLink": "/ec2/concept/5982489"
    }
  },
  {
    "uri": "en/41/849519",
    "id": "849519",
    "lang": "en",
    "classNumber": "41",
    "term": "Educational services relating to information technology",
    "harm": {
      "id": "0046017",
      "title": "849519 - Educational services relating to information technology",
      "conceptLink": "/ec2/concept/5993533"
    }
  },
  {
    "uri": "en/41/849613",
    "id": "849613",
    "lang": "en",
    "classNumber": "41",
    "term": "Educational services relating to the teaching of foreign languages",
    "harm": {
      "id": "0039093",
      "title": "849613 - Educational services relating to the teaching of foreign languages",
      "conceptLink": "/ec2/concept/5987196"
    }
  },
  {
    "uri": "en/41/232029123",
    "id": "232029123",
    "lang": "en",
    "classNumber": "41",
    "term": "Educational services relating to Japanese cuisine",
    "harm": {
      "id": "0071221",
      "title": "232029123 - Educational services relating to Japanese cuisine",
      "conceptLink": "/ec2/concept/6007413"
    }
  },
  {
    "uri": "en/41/849455",
    "id": "849455",
    "lang": "en",
    "classNumber": "41",
    "term": "Educational services relating to architecture",
    "harm": {
      "id": "0044039",
      "title": "849455 - Educational services relating to architecture",
      "conceptLink": "/ec2/concept/5991715"
    }
  },
  {
    "uri": "en/41/846097",
    "id": "846097",
    "lang": "en",
    "classNumber": "41",
    "term": "Educational services relating to business",
    "harm": {
      "id": "0057170",
      "title": "846097 - Educational services relating to business",
      "conceptLink": "/ec2/concept/5998790"
    }
  },
  {
    "uri": "en/41/849494",
    "id": "849494",
    "lang": "en",
    "classNumber": "41",
    "term": "Educational services relating to dancing",
    "harm": {
      "id": "0040301",
      "title": "849494 - Educational services relating to dancing",
      "conceptLink": "/ec2/concept/5988307"
    }
  },
  {
    "uri": "en/41/849506",
    "id": "849506",
    "lang": "en",
    "classNumber": "41",
    "term": "Educational services relating to first aid",
    "harm": {
      "id": "0040302",
      "title": "849506 - Educational services relating to first aid",
      "conceptLink": "/ec2/concept/5988308"
    }
  },
  {
    "uri": "en/41/849575",
    "id": "849575",
    "lang": "en",
    "classNumber": "41",
    "term": "Educational services relating to spiritual development",
    "harm": {
      "id": "0040303",
      "title": "849575 - Educational services relating to spiritual development",
      "conceptLink": "/ec2/concept/5988309"
    }
  },
  {
    "uri": "en/41/849638",
    "id": "849638",
    "lang": "en",
    "classNumber": "41",
    "term": "Educational services relating to the writing of computer programs",
    "harm": {
      "id": "0044818",
      "title": "849638 - Educational services relating to the writing of computer programs",
      "conceptLink": "/ec2/concept/5992432"
    }
  },
  {
    "uri": "en/41/463926",
    "id": "463926",
    "lang": "en",
    "classNumber": "41",
    "term": "Educational testing",
    "harm": {
      "id": "0028383",
      "title": "463926 - Educational testing",
      "conceptLink": "/ec2/concept/5977439"
    }
  },
  {
    "uri": "en/41/137613672",
    "id": "137613672",
    "lang": "en",
    "classNumber": "41",
    "term": "Electronic book reader rental",
    "harm": {
      "id": "0060879",
      "title": "137613672 - Electronic book reader rental",
      "conceptLink": "/ec2/concept/6001199"
    }
  },
  {
    "uri": "en/41/463942",
    "id": "463942",
    "lang": "en",
    "classNumber": "41",
    "term": "Electronic data processing training",
    "harm": {
      "id": "0028384",
      "title": "463942 - Electronic data processing training",
      "conceptLink": "/ec2/concept/5977440"
    }
  },
  {
    "uri": "en/41/60618",
    "id": "60618",
    "lang": "en",
    "classNumber": "41",
    "term": "Electronic desktop publishing",
    "harm": {
      "id": "0018732",
      "title": "60618 - Electronic desktop publishing",
      "conceptLink": "/ec2/concept/5968612"
    }
  },
  {
    "uri": "en/41/463989",
    "id": "463989",
    "lang": "en",
    "classNumber": "41",
    "term": "Electronic game services provided by means of the internet",
    "harm": {
      "id": "0024521",
      "title": "463989 - Electronic game services provided by means of the internet",
      "conceptLink": "/ec2/concept/5973902"
    }
  },
  {
    "uri": "en/41/463963",
    "id": "463963",
    "lang": "en",
    "classNumber": "41",
    "term": "Electronic game services and competitions provided by means of the internet",
    "harm": {
      "id": "0022714",
      "title": "463963 - Electronic game services and competitions provided by means of the internet",
      "conceptLink": "/ec2/concept/5972246"
    }
  },
  {
    "uri": "en/41/463988",
    "id": "463988",
    "lang": "en",
    "classNumber": "41",
    "term": "Electronic games services provided by means of the internet",
    "harm": {
      "id": "0024521",
      "title": "463988 - Electronic games services provided by means of the internet",
      "conceptLink": "/ec2/concept/5973902"
    }
  },
  {
    "uri": "en/41/482064",
    "id": "482064",
    "lang": "en",
    "classNumber": "41",
    "term": "Electronic games services provided from a computer database or by means of the internet",
    "harm": {
      "id": "0013333",
      "title": "482064 - Electronic games services provided from a computer database or by means of the internet",
      "conceptLink": "/ec2/concept/5963659"
    }
  },
  {
    "uri": "en/41/120870388",
    "id": "120870388",
    "lang": "en",
    "classNumber": "41",
    "term": "Electronic games services provided by means of a global communication network",
    "harm": {
      "id": "0069095",
      "title": "120870388 - Electronic games services provided by means of a global communication network",
      "conceptLink": "/ec2/concept/6005298"
    }
  },
  {
    "uri": "en/41/482097",
    "id": "482097",
    "lang": "en",
    "classNumber": "41",
    "term": "Electronic games services, including provision of computer games on-line or by means of a global computer network",
    "harm": {
      "id": "0042198",
      "title": "482097 - Electronic games services, including provision of computer games on-line or by means of a global computer network",
      "conceptLink": "/ec2/concept/5990040"
    }
  },
  {
    "uri": "en/41/482078",
    "id": "482078",
    "lang": "en",
    "classNumber": "41",
    "term": "Electronic games services provided via a global computer network",
    "harm": {
      "id": "0042197",
      "title": "482078 - Electronic games services provided via a global computer network",
      "conceptLink": "/ec2/concept/5990039"
    }
  },
  {
    "uri": "en/41/849665",
    "id": "849665",
    "lang": "en",
    "classNumber": "41",
    "term": "Electronic library services",
    "harm": {
      "id": "0004452",
      "title": "849665 - Electronic library services",
      "conceptLink": "/ec2/concept/5955525"
    }
  },
  {
    "uri": "en/41/482125",
    "id": "482125",
    "lang": "en",
    "classNumber": "41",
    "term": "Electronic library services for the supply of electronic information (including archive information) in the form of text, audio and/or video information",
    "harm": {
      "id": "0028129",
      "title": "482125 - Electronic library services for the supply of electronic information (including archive information) in the form of text, audio and/or video information",
      "conceptLink": "/ec2/concept/5977199"
    }
  },
  {
    "uri": "en/41/914759",
    "id": "914759",
    "lang": "en",
    "classNumber": "41",
    "term": "Electronic online publication of periodicals and books",
    "harm": {
      "id": "0022715",
      "title": "914759 - Electronic online publication of periodicals and books",
      "conceptLink": "/ec2/concept/5972247"
    }
  },
  {
    "uri": "en/41/482166",
    "id": "482166",
    "lang": "en",
    "classNumber": "41",
    "term": "Electronic publication",
    "harm": {
      "id": "0018732",
      "title": "482166 - Electronic publication",
      "conceptLink": "/ec2/concept/5968612"
    }
  },
  {
    "uri": "en/41/120876597",
    "id": "120876597",
    "lang": "en",
    "classNumber": "41",
    "term": "Electronic publication of texts and printed matter, other than publicity texts, on the Internet",
    "harm": {
      "id": "0068985",
      "title": "120876597 - Electronic publication of texts and printed matter, other than publicity texts, on the Internet",
      "conceptLink": "/ec2/concept/6005188"
    }
  },
  {
    "uri": "en/41/482168",
    "id": "482168",
    "lang": "en",
    "classNumber": "41",
    "term": "Electronic publication services",
    "harm": {
      "id": "0018732",
      "title": "482168 - Electronic publication services",
      "conceptLink": "/ec2/concept/5968612"
    }
  },
  {
    "uri": "en/41/467635",
    "id": "467635",
    "lang": "en",
    "classNumber": "41",
    "term": "Electronic publications (not downloadable)",
    "harm": {
      "id": "0029506",
      "title": "467635 - Electronic publications (not downloadable)",
      "conceptLink": "/ec2/concept/5978470"
    }
  },
  {
    "uri": "en/41/482165",
    "id": "482165",
    "lang": "en",
    "classNumber": "41",
    "term": "Electronic publishing",
    "harm": {
      "id": "0018732",
      "title": "482165 - Electronic publishing",
      "conceptLink": "/ec2/concept/5968612"
    }
  },
  {
    "uri": "en/41/482167",
    "id": "482167",
    "lang": "en",
    "classNumber": "41",
    "term": "Electronic publishing services",
    "harm": {
      "id": "0018732",
      "title": "482167 - Electronic publishing services",
      "conceptLink": "/ec2/concept/5968612"
    }
  },
  {
    "uri": "en/41/849679",
    "id": "849679",
    "lang": "en",
    "classNumber": "41",
    "term": "Electronic text publishing services",
    "harm": {
      "id": "0027516",
      "title": "849679 - Electronic text publishing services",
      "conceptLink": "/ec2/concept/5976635"
    }
  },
  {
    "uri": "en/41/849693",
    "id": "849693",
    "lang": "en",
    "classNumber": "41",
    "term": "Electronic viewing guide services",
    "harm": {
      "id": "0021899",
      "title": "849693 - Electronic viewing guide services",
      "conceptLink": "/ec2/concept/5971498"
    }
  },
  {
    "uri": "en/41/849707",
    "id": "849707",
    "lang": "en",
    "classNumber": "41",
    "term": "Engineering training college services",
    "harm": {
      "id": "0044819",
      "title": "849707 - Engineering training college services",
      "conceptLink": "/ec2/concept/5992433"
    }
  },
  {
    "uri": "en/41/849719",
    "id": "849719",
    "lang": "en",
    "classNumber": "41",
    "term": "English language education services",
    "harm": {
      "id": "0004453",
      "title": "849719 - English language education services",
      "conceptLink": "/ec2/concept/5955526"
    }
  },
  {
    "uri": "en/41/55010",
    "id": "55010",
    "lang": "en",
    "classNumber": "41",
    "term": "Entertainer services",
    "harm": {
      "id": "0025736",
      "title": "55010 - Entertainer services",
      "conceptLink": "/ec2/concept/5975018"
    }
  },
  {
    "uri": "en/41/849734",
    "id": "849734",
    "lang": "en",
    "classNumber": "41",
    "term": "Entertainer services provided by musicians",
    "harm": {
      "id": "0017193",
      "title": "849734 - Entertainer services provided by musicians",
      "conceptLink": "/ec2/concept/5967197"
    }
  },
  {
    "uri": "en/41/849748",
    "id": "849748",
    "lang": "en",
    "classNumber": "41",
    "term": "Entertainer services utilizing circus skills",
    "harm": {
      "id": "0005668",
      "title": "849748 - Entertainer services utilizing circus skills",
      "conceptLink": "/ec2/concept/5956648"
    }
  },
  {
    "uri": "en/41/54827",
    "id": "54827",
    "lang": "en",
    "classNumber": "41",
    "term": "Entertainment",
    "harm": {
      "id": "0007836",
      "title": "54827 - Entertainment",
      "conceptLink": "/ec2/concept/5958630"
    }
  },
  {
    "uri": "en/41/849760",
    "id": "849760",
    "lang": "en",
    "classNumber": "41",
    "term": "Entertainment agency services",
    "harm": {
      "id": "0028715",
      "title": "849760 - Entertainment agency services",
      "conceptLink": "/ec2/concept/5977749"
    }
  },
  {
    "uri": "en/41/464066",
    "id": "464066",
    "lang": "en",
    "classNumber": "41",
    "term": "Entertainment booking services",
    "harm": {
      "id": "0011053",
      "title": "464066 - Entertainment booking services",
      "conceptLink": "/ec2/concept/5961575"
    }
  },
  {
    "uri": "en/41/849774",
    "id": "849774",
    "lang": "en",
    "classNumber": "41",
    "term": "Entertainment by film",
    "harm": {
      "id": "0017194",
      "title": "849774 - Entertainment by film",
      "conceptLink": "/ec2/concept/5967198"
    }
  },
  {
    "uri": "en/41/120869939",
    "id": "120869939",
    "lang": "en",
    "classNumber": "41",
    "term": "Entertainment by IP-TV",
    "harm": {
      "id": "0069030",
      "title": "120869939 - Entertainment by IP-TV",
      "conceptLink": "/ec2/concept/6005233"
    }
  },
  {
    "uri": "en/41/849789",
    "id": "849789",
    "lang": "en",
    "classNumber": "41",
    "term": "Entertainment by means of concerts",
    "harm": {
      "id": "0011390",
      "title": "849789 - Entertainment by means of concerts",
      "conceptLink": "/ec2/concept/5961879"
    }
  },
  {
    "uri": "en/41/55519",
    "id": "55519",
    "lang": "en",
    "classNumber": "41",
    "term": "Entertainment by means of radio",
    "harm": {
      "id": "0011787",
      "title": "55519 - Entertainment by means of radio",
      "conceptLink": "/ec2/concept/5962246"
    }
  },
  {
    "uri": "en/41/57171",
    "id": "57171",
    "lang": "en",
    "classNumber": "41",
    "term": "Entertainment by means of television",
    "harm": {
      "id": "0024334",
      "title": "57171 - Entertainment by means of television",
      "conceptLink": "/ec2/concept/5973734"
    }
  },
  {
    "uri": "en/41/849817",
    "id": "849817",
    "lang": "en",
    "classNumber": "41",
    "term": "Entertainment by means of telephone",
    "harm": {
      "id": "0001150",
      "title": "849817 - Entertainment by means of telephone",
      "conceptLink": "/ec2/concept/5952523"
    }
  },
  {
    "uri": "en/41/464511",
    "id": "464511",
    "lang": "en",
    "classNumber": "41",
    "term": "Entertainment by means of theatre productions",
    "harm": {
      "id": "0032579",
      "title": "464511 - Entertainment by means of theatre productions",
      "conceptLink": "/ec2/concept/5981267"
    }
  },
  {
    "uri": "en/41/849802",
    "id": "849802",
    "lang": "en",
    "classNumber": "41",
    "term": "Entertainment by means of roadshows",
    "harm": {
      "id": "0045997",
      "title": "849802 - Entertainment by means of roadshows",
      "conceptLink": "/ec2/concept/5993514"
    }
  },
  {
    "uri": "en/41/15585259",
    "id": "15585259",
    "lang": "en",
    "classNumber": "41",
    "term": "Entertainment by means of wireless television broadcasts",
    "harm": {
      "id": "0069054",
      "title": "15585259 - Entertainment by means of wireless television broadcasts",
      "conceptLink": "/ec2/concept/6005257"
    }
  },
  {
    "uri": "en/41/480451",
    "id": "480451",
    "lang": "en",
    "classNumber": "41",
    "term": "Entertainment club services",
    "harm": {
      "id": "0031038",
      "title": "480451 - Entertainment club services",
      "conceptLink": "/ec2/concept/5979880"
    }
  },
  {
    "uri": "en/41/482285",
    "id": "482285",
    "lang": "en",
    "classNumber": "41",
    "term": "Entertainment, education and instruction services",
    "harm": {
      "id": "0040232",
      "title": "482285 - Entertainment, education and instruction services",
      "conceptLink": "/ec2/concept/5988245"
    }
  },
  {
    "uri": "en/41/124719885",
    "id": "124719885",
    "lang": "en",
    "classNumber": "41",
    "term": "Entertainment in the form of live musical performances (Services providing -)",
    "harm": {
      "id": "0002357",
      "title": "124719885 - Entertainment in the form of live musical performances (Services providing -)",
      "conceptLink": "/ec2/concept/5953610"
    }
  },
  {
    "uri": "en/41/125072003",
    "id": "125072003",
    "lang": "en",
    "classNumber": "41",
    "term": "Entertainment in the form of television programmes (Services providing -)",
    "harm": {
      "id": "0026991",
      "title": "125072003 - Entertainment in the form of television programmes (Services providing -)",
      "conceptLink": "/ec2/concept/5976159"
    }
  },
  {
    "uri": "en/41/125071988",
    "id": "125071988",
    "lang": "en",
    "classNumber": "41",
    "term": "Entertainment in the form of recorded music (Services providing -)",
    "harm": {
      "id": "0032733",
      "title": "125071988 - Entertainment in the form of recorded music (Services providing -)",
      "conceptLink": "/ec2/concept/5981409"
    }
  },
  {
    "uri": "en/41/464147",
    "id": "464147",
    "lang": "en",
    "classNumber": "41",
    "term": "Entertainment in the nature of air shows",
    "harm": {
      "id": "0001892",
      "title": "464147 - Entertainment in the nature of air shows",
      "conceptLink": "/ec2/concept/5953192"
    }
  },
  {
    "uri": "en/41/464208",
    "id": "464208",
    "lang": "en",
    "classNumber": "41",
    "term": "Entertainment in the nature of basketball games",
    "harm": {
      "id": "0001893",
      "title": "464208 - Entertainment in the nature of basketball games",
      "conceptLink": "/ec2/concept/5953193"
    }
  },
  {
    "uri": "en/41/464248",
    "id": "464248",
    "lang": "en",
    "classNumber": "41",
    "term": "Entertainment in the nature of circuses",
    "harm": {
      "id": "0001894",
      "title": "464248 - Entertainment in the nature of circuses",
      "conceptLink": "/ec2/concept/5953194"
    }
  },
  {
    "uri": "en/41/464559",
    "id": "464559",
    "lang": "en",
    "classNumber": "41",
    "term": "Entertainment in the nature of wrestling contests",
    "harm": {
      "id": "0003732",
      "title": "464559 - Entertainment in the nature of wrestling contests",
      "conceptLink": "/ec2/concept/5954866"
    }
  },
  {
    "uri": "en/41/464135",
    "id": "464135",
    "lang": "en",
    "classNumber": "41",
    "term": "Entertainment in the nature of yacht races",
    "harm": {
      "id": "0007616",
      "title": "464135 - Entertainment in the nature of yacht races",
      "conceptLink": "/ec2/concept/5958426"
    }
  },
  {
    "uri": "en/41/464162",
    "id": "464162",
    "lang": "en",
    "classNumber": "41",
    "term": "Entertainment in the nature of an amusement park ride",
    "harm": {
      "id": "0025043",
      "title": "464162 - Entertainment in the nature of an amusement park ride",
      "conceptLink": "/ec2/concept/5974389"
    }
  },
  {
    "uri": "en/41/464288",
    "id": "464288",
    "lang": "en",
    "classNumber": "41",
    "term": "Entertainment in the nature of fashion shows",
    "harm": {
      "id": "0025044",
      "title": "464288 - Entertainment in the nature of fashion shows",
      "conceptLink": "/ec2/concept/5974390"
    }
  },
  {
    "uri": "en/41/464120",
    "id": "464120",
    "lang": "en",
    "classNumber": "41",
    "term": "Entertainment in the nature of tennis tournaments",
    "harm": {
      "id": "0025042",
      "title": "464120 - Entertainment in the nature of tennis tournaments",
      "conceptLink": "/ec2/concept/5974388"
    }
  },
  {
    "uri": "en/41/464181",
    "id": "464181",
    "lang": "en",
    "classNumber": "41",
    "term": "Entertainment in the nature of ballet performances",
    "harm": {
      "id": "0013467",
      "title": "464181 - Entertainment in the nature of ballet performances",
      "conceptLink": "/ec2/concept/5963781"
    }
  },
  {
    "uri": "en/41/464196",
    "id": "464196",
    "lang": "en",
    "classNumber": "41",
    "term": "Entertainment in the nature of baseball games",
    "harm": {
      "id": "0013468",
      "title": "464196 - Entertainment in the nature of baseball games",
      "conceptLink": "/ec2/concept/5963782"
    }
  },
  {
    "uri": "en/41/464263",
    "id": "464263",
    "lang": "en",
    "classNumber": "41",
    "term": "Entertainment in the nature of competitions in the field of spelling",
    "harm": {
      "id": "0013469",
      "title": "464263 - Entertainment in the nature of competitions in the field of spelling",
      "conceptLink": "/ec2/concept/5963783"
    }
  },
  {
    "uri": "en/41/464467",
    "id": "464467",
    "lang": "en",
    "classNumber": "41",
    "term": "Entertainment in the nature of roller derbys",
    "harm": {
      "id": "0011302",
      "title": "464467 - Entertainment in the nature of roller derbys",
      "conceptLink": "/ec2/concept/5961800"
    }
  },
  {
    "uri": "en/41/464303",
    "id": "464303",
    "lang": "en",
    "classNumber": "41",
    "term": "Entertainment in the nature of football games",
    "harm": {
      "id": "0026803",
      "title": "464303 - Entertainment in the nature of football games",
      "conceptLink": "/ec2/concept/5975987"
    }
  },
  {
    "uri": "en/41/464304",
    "id": "464304",
    "lang": "en",
    "classNumber": "41",
    "term": "Entertainment in the nature of soccer games",
    "harm": {
      "id": "0026803",
      "title": "464304 - Entertainment in the nature of soccer games",
      "conceptLink": "/ec2/concept/5975987"
    }
  },
  {
    "uri": "en/41/137806563",
    "id": "137806563",
    "lang": "en",
    "classNumber": "41",
    "term": "Entertainment in the nature of live performances by rock groups",
    "harm": {
      "id": "0027708",
      "title": "137806563 - Entertainment in the nature of live performances by rock groups",
      "conceptLink": "/ec2/concept/5976819"
    }
  },
  {
    "uri": "en/41/464236",
    "id": "464236",
    "lang": "en",
    "classNumber": "41",
    "term": "Entertainment in the nature of boxing contests",
    "harm": {
      "id": "0036598",
      "title": "464236 - Entertainment in the nature of boxing contests",
      "conceptLink": "/ec2/concept/5984926"
    }
  },
  {
    "uri": "en/41/464439",
    "id": "464439",
    "lang": "en",
    "classNumber": "41",
    "term": "Entertainment in the nature of orchestra performances",
    "harm": {
      "id": "0034419",
      "title": "464439 - Entertainment in the nature of orchestra performances",
      "conceptLink": "/ec2/concept/5982953"
    }
  },
  {
    "uri": "en/41/464454",
    "id": "464454",
    "lang": "en",
    "classNumber": "41",
    "term": "Entertainment in the nature of prerecorded sex-oriented messages by telephone",
    "harm": {
      "id": "0034420",
      "title": "464454 - Entertainment in the nature of prerecorded sex-oriented messages by telephone",
      "conceptLink": "/ec2/concept/5982954"
    }
  },
  {
    "uri": "en/41/464363",
    "id": "464363",
    "lang": "en",
    "classNumber": "41",
    "term": "Entertainment in the nature of laser shows",
    "harm": {
      "id": "0034418",
      "title": "464363 - Entertainment in the nature of laser shows",
      "conceptLink": "/ec2/concept/5982952"
    }
  },
  {
    "uri": "en/41/464321",
    "id": "464321",
    "lang": "en",
    "classNumber": "41",
    "term": "Entertainment in the nature of golf tournaments",
    "harm": {
      "id": "0005574",
      "title": "464321 - Entertainment in the nature of golf tournaments",
      "conceptLink": "/ec2/concept/5956566"
    }
  },
  {
    "uri": "en/41/137806679",
    "id": "137806679",
    "lang": "en",
    "classNumber": "41",
    "term": "Entertainment in the nature of live performances by musical bands",
    "harm": {
      "id": "0006041",
      "title": "137806679 - Entertainment in the nature of live performances by musical bands",
      "conceptLink": "/ec2/concept/5956986"
    }
  },
  {
    "uri": "en/41/464427",
    "id": "464427",
    "lang": "en",
    "classNumber": "41",
    "term": "Entertainment in the nature of on-going television programs in the field of variety",
    "harm": {
      "id": "0017102",
      "title": "464427 - Entertainment in the nature of on-going television programs in the field of variety",
      "conceptLink": "/ec2/concept/5967115"
    }
  },
  {
    "uri": "en/41/464391",
    "id": "464391",
    "lang": "en",
    "classNumber": "41",
    "term": "Entertainment in the nature of magic shows",
    "harm": {
      "id": "0017101",
      "title": "464391 - Entertainment in the nature of magic shows",
      "conceptLink": "/ec2/concept/5967114"
    }
  },
  {
    "uri": "en/41/464336",
    "id": "464336",
    "lang": "en",
    "classNumber": "41",
    "term": "Entertainment in the nature of gymnastic performances",
    "harm": {
      "id": "0017099",
      "title": "464336 - Entertainment in the nature of gymnastic performances",
      "conceptLink": "/ec2/concept/5967112"
    }
  },
  {
    "uri": "en/41/137699455",
    "id": "137699455",
    "lang": "en",
    "classNumber": "41",
    "term": "Entertainment in the nature of ongoing television programs in the field of variety",
    "harm": {
      "id": "0017102",
      "title": "137699455 - Entertainment in the nature of ongoing television programs in the field of variety",
      "conceptLink": "/ec2/concept/5967115"
    }
  },
  {
    "uri": "en/41/464377",
    "id": "464377",
    "lang": "en",
    "classNumber": "41",
    "term": "Entertainment in the nature of light shows",
    "harm": {
      "id": "0017100",
      "title": "464377 - Entertainment in the nature of light shows",
      "conceptLink": "/ec2/concept/5967113"
    }
  },
  {
    "uri": "en/41/464275",
    "id": "464275",
    "lang": "en",
    "classNumber": "41",
    "term": "Entertainment in the nature of dance performances",
    "harm": {
      "id": "0030777",
      "title": "464275 - Entertainment in the nature of dance performances",
      "conceptLink": "/ec2/concept/5979648"
    }
  },
  {
    "uri": "en/41/464109",
    "id": "464109",
    "lang": "en",
    "classNumber": "41",
    "term": "Entertainment in the nature of ice hockey games",
    "harm": {
      "id": "0022716",
      "title": "464109 - Entertainment in the nature of ice hockey games",
      "conceptLink": "/ec2/concept/5972248"
    }
  }
]